src/__init__.py
src/app.py
docmake-0.1.6.dist-info/LICENSE
docmake-0.1.6.dist-info/METADATA
docmake-0.1.6.dist-info/WHEEL
docmake-0.1.6.dist-info/entry_points.txt
docmake-0.1.6.dist-info/RECORD
