Metadata-Version: 2.1
Name: docmake
Version: 0.1.6
Summary: Generate pdf files from other format documents.
Home-page: https://github.com/morisono/docmaker_webui
Author: admin
Requires-Python: >=3.10,<4.0
Classifier: Programming Language :: Python :: 3
Classifier: Programming Language :: Python :: 3.10
Classifier: Programming Language :: Python :: 3.11
Classifier: Programming Language :: Python :: 3.12
Project-URL: Repository, https://github.com/morisono/docmaker_webui
